LICENSE
MANIFEST.in
README.md
pyproject.toml
setup.py
pystemd/__init__.py
pystemd/__init__.pyi
pystemd/__version__.py
pystemd/base.py
pystemd/cutils.c
pystemd/cutils.pyi
pystemd/cutils.pyx
pystemd/daemon.c
pystemd/daemon.pyi
pystemd/daemon.pyx
pystemd/dbusc.pxd
pystemd/dbusc_v237.pxi
pystemd/dbusexc.c
pystemd/dbusexc.pyx
pystemd/dbuslib.c
pystemd/dbuslib.pyi
pystemd/dbuslib.pyx
pystemd/exceptions.py
pystemd/futures.py
pystemd/journal.c
pystemd/journal.pyx
pystemd/run.py
pystemd/utils.py
pystemd.egg-info/PKG-INFO
pystemd.egg-info/SOURCES.txt
pystemd.egg-info/dependency_links.txt
pystemd.egg-info/requires.txt
pystemd.egg-info/top_level.txt
pystemd/DBus/__init__.py
pystemd/machine1/__init__.py
pystemd/machine1/machine.py
pystemd/machine1/manager.py
pystemd/systemd1/__init__.py
pystemd/systemd1/manager.py
pystemd/systemd1/manager.pyi
pystemd/systemd1/unit.py
pystemd/systemd1/unit.pyi
pystemd/systemd1/unit_signatures.py
tests/test_base.py
tests/test_daemon.py
tests/test_dbus_arg_parsing.py
tests/test_dbuslib.py
tests/test_futures.py
tests/test_journal.py
tests/test_pickle.py
tests/test_unit_signatures.py
tests/test_utils.py
tests/test_version.py