Metadata-Version: 2.4
Name: pystemd
Version: 0.15.1
Summary: A systemd binding for python
Author: Alvaro Leiva Geisse
Author-email: Alvaro Leiva Geisse <aleivag@gmail.com>
Maintainer-email: Alvaro Leiva Geisse <aleivag@gmail.com>, Davide Cavalca <dcavalca@meta.com>, Anita Zhang <the.anitazha@gmail.com>
License: LGPL-2.1+
Project-URL: changelog, https://github.com/systemd/pystemd/blob/main/CHANGES.md
Project-URL: homepage, https://github.com/systemd/pystemd
Project-URL: repository, https://github.com/systemd/pystemd.git
Keywords: systemd,linux,dbus
Classifier: Operating System :: POSIX :: Linux
Classifier: Intended Audience :: Developers
Classifier: Intended Audience :: System Administrators
Classifier: Programming Language :: Python :: 3.10
Classifier: Programming Language :: Python :: 3.11
Classifier: Programming Language :: Python :: 3.12
Classifier: Programming Language :: Python :: 3.13
Classifier: Programming Language :: Python :: 3.14
Classifier: Development Status :: 5 - Production/Stable
Classifier: Topic :: Utilities
Classifier: License :: OSI Approved :: GNU Lesser General Public License v2 or later (LGPLv2+)
Requires-Python: >=3.11
License-File: LICENSE
Requires-Dist: lxml
Requires-Dist: psutil
Provides-Extra: t
Requires-Dist: pytest; extra == "t"
Requires-Dist: pytest-cov; extra == "t"
Requires-Dist: cstq; extra == "t"
Requires-Dist: toml; extra == "t"
Provides-Extra: lint
Requires-Dist: ruff; extra == "lint"
Requires-Dist: pyrefly; extra == "lint"
Requires-Dist: isort; extra == "lint"
Dynamic: author
Dynamic: license-file
